mkdocs_izsam_mermaid_to_images/__init__.py
mkdocs_izsam_mermaid_to_images/plugin.py
mkdocs_izsam_mermaid_to_images-1.1.dist-info/LICENSE.txt
mkdocs_izsam_mermaid_to_images-1.1.dist-info/METADATA
mkdocs_izsam_mermaid_to_images-1.1.dist-info/WHEEL
mkdocs_izsam_mermaid_to_images-1.1.dist-info/entry_points.txt
mkdocs_izsam_mermaid_to_images-1.1.dist-info/top_level.txt
mkdocs_izsam_mermaid_to_images-1.1.dist-info/RECORD
