Metadata-Version: 2.1
Name: mkdocs-izsam-mermaid-to-images
Version: 1.1
Summary: MkDocs plugin to convert Mermaid code blocks to images.
Home-page: UNKNOWN
Author: Alessandro De Luca
Author-email: al.deluca@izs.it
License: MIT
Keywords: MkDocs,Mermaid,Mermaid to images
Platform: UNKNOWN
Requires-Python: >=3.8
License-File: LICENSE.txt
Requires-Dist: mkdocs (>=1.0.4)
